<?xml version="1.0"?>
<opencv_storage>
<stage14>
  <maxWeakCount>94</maxWeakCount>
  <stageThreshold>-8.9817982912063599e-01</stageThreshold>
  <weakClassifiers>
    <_>
      <internalNodes>
        0 -1 122795 1.3101980090141296e-01</internalNodes>
      <leafValues>
        -9.6746012568473816e-02 2.2133758664131165e-01</leafValues></_>
    <_>
      <internalNodes>
        0 -1 107430 1.8875236855819821e-04</internalNodes>
      <leafValues>
        7.8946121037006378e-02 -1.8313235044479370e-01</leafValues></_>
    <_>
      <internalNodes>
        0 -1 27841 -2.6041879318654537e-03</internalNodes>
      <leafValues>
        1.3017739355564117e-01 -1.0498297959566116e-01</leafValues></_>
    <_>
      <internalNodes>
        0 -1 143828 -3.7107756361365318e-03</internalNodes>
      <leafValues>
        -8.7746417522430420e-01 -1.4259892515838146e-02</leafValues></_>
    <_>
      <internalNodes>
        0 -1 36902 7.1112397126853466e-03</internalNodes>
      <leafValues>
        7.1227297186851501e-02 -2.3494403064250946e-01</leafValues></_>
    <_>
      <internalNodes>
        0 -1 33081 -9.2097841203212738e-02</internalNodes>
      <leafValues>
        2.8676187992095947e-01 -4.6835936605930328e-02</leafValues></_>
    <_>
      <internalNodes>
        0 -1 53049 3.8317956030368805e-02</internalNodes>
      <leafValues>
        -1.0423727333545685e-01 1.9412867724895477e-01</leafValues></_>
    <_>
      <internalNodes>
        0 -1 95238 -3.1913660932332277e-03</internalNodes>
      <leafValues>
        3.2876947522163391e-01 -1.8390920013189316e-02</leafValues></_>
    <_>
      <internalNodes>
        0 -1 57091 -6.6967261955142021e-03</internalNodes>
      <leafValues>
        -2.7919074892997742e-01 4.8807591199874878e-02</leafValues></_>
    <_>
      <internalNodes>
        0 -1 46005 -6.0607865452766418e-03</internalNodes>
      <leafValues>
        2.2239971160888672e-01 -5.8218475431203842e-02</leafValues></_>
    <_>
      <internalNodes>
        0 -1 56436 -5.4127648472785950e-03</internalNodes>
      <leafValues>
        -1.8993723392486572e-01 6.6203869879245758e-02</leafValues></_>
    <_>
      <internalNodes>
        0 -1 140067 3.2756097614765167e-02</internalNodes>
      <leafValues>
        4.3611712753772736e-02 -9.2531383037567139e-01</leafValues></_>
    <_>
      <internalNodes>
        0 -1 139274 -5.8686356991529465e-02</internalNodes>
      <leafValues>
        5.5898123979568481e-01 -3.8063738495111465e-02</leafValues></_>
    <_>
      <internalNodes>
        0 -1 104532 4.9381656572222710e-03</internalNodes>
      <leafValues>
        -1.1009937524795532e-01 1.4999642968177795e-01</leafValues></_>
    <_>
      <internalNodes>
        0 -1 36714 -9.2337112873792648e-03</internalNodes>
      <leafValues>
        4.7657307982444763e-01 -3.0822018161416054e-02</leafValues></_>
    <_>
      <internalNodes>
        0 -1 12089 1.1732069775462151e-02</internalNodes>
      <leafValues>
        3.4610033035278320e-02 -6.8498718738555908e-01</leafValues></_>
    <_>
      <internalNodes>
        0 -1 11516 4.8422423424199224e-04</internalNodes>
      <leafValues>
        6.9582410156726837e-02 -2.0838937163352966e-01</leafValues></_>
    <_>
      <internalNodes>
        0 -1 24079 -3.6248918622732162e-03</internalNodes>
      <leafValues>
        1.9780471920967102e-01 -7.0180945098400116e-02</leafValues></_>
    <_>
      <internalNodes>
        0 -1 49480 1.8150793039239943e-04</internalNodes>
      <leafValues>
        6.2128815799951553e-02 -2.2415706515312195e-01</leafValues></_>
    <_>
      <internalNodes>
        0 -1 14646 2.5471204426139593e-03</internalNodes>
      <leafValues>
        -7.9872220754623413e-02 1.6482375562191010e-01</leafValues></_>
    <_>
      <internalNodes>
        0 -1 14660 1.5280270017683506e-02</internalNodes>
      <leafValues>
        -7.8900098800659180e-02 2.4488532543182373e-01</leafValues></_>
    <_>
      <internalNodes>
        0 -1 18929 -2.3629455827176571e-03</internalNodes>
      <leafValues>
        1.6315259039402008e-01 -9.6226312220096588e-02</leafValues></_>
    <_>
      <internalNodes>
        0 -1 158102 -1.5275340410880744e-04</internalNodes>
      <leafValues>
        -1.7682191729545593e-01 1.0172192752361298e-01</leafValues></_>
    <_>
      <internalNodes>
        0 -1 160539 3.6047687754034996e-03</internalNodes>
      <leafValues>
        9.2894211411476135e-03 -1.</leafValues></_>
    <_>
      <internalNodes>
        0 -1 64005 1.3873684406280518e-01</internalNodes>
      <leafValues>
        4.6968962997198105e-02 -3.4353917837142944e-01</leafValues></_>
    <_>
      <internalNodes>
        0 -1 4230 4.5552942901849747e-03</internalNodes>
      <leafValues>
        8.3241894841194153e-02 -1.7414364218711853e-01</leafValues></_>
    <_>
      <internalNodes>
        0 -1 16314 7.5475042685866356e-03</internalNodes>
      <leafValues>
        -6.4532600343227386e-02 2.6314225792884827e-01</leafValues></_>
    <_>
      <internalNodes>
        0 -1 58170 -9.0169941540807486e-04</internalNodes>
      <leafValues>
        1.2467700988054276e-01 -1.0849674791097641e-01</leafValues></_>
    <_>
      <internalNodes>
        0 -1 58223 -6.3513845205307007e-02</internalNodes>
      <leafValues>
        -5.8554005622863770e-01 2.1416978910565376e-02</leafValues></_>
    <_>
      <internalNodes>
        0 -1 120457 3.9167385548353195e-02</internalNodes>
      <leafValues>
        -3.8223102688789368e-02 3.5155603289604187e-01</leafValues></_>
    <_>
      <internalNodes>
        0 -1 153144 4.0006218478083611e-03</internalNodes>
      <leafValues>
        -4.7001890838146210e-02 3.2835412025451660e-01</leafValues></_>
    <_>
      <internalNodes>
        0 -1 89904 -4.9611916765570641e-03</internalNodes>
      <leafValues>
        -6.6061067581176758e-01 1.9048957154154778e-02</leafValues></_>
    <_>
      <internalNodes>
        0 -1 120045 -4.8158541321754456e-03</internalNodes>
      <leafValues>
        -3.4936583042144775e-01 3.7188272923231125e-02</leafValues></_>
    <_>
      <internalNodes>
        0 -1 32593 -2.5669683236628771e-03</internalNodes>
      <leafValues>
        -2.8515267372131348e-01 4.8392448574304581e-02</leafValues></_>
    <_>
      <internalNodes>
        0 -1 132525 -1.5479015186429024e-02</internalNodes>
      <leafValues>
        1.6469877958297729e-01 -7.7699385583400726e-02</leafValues></_>
    <_>
      <internalNodes>
        0 -1 89418 7.9845394939184189e-03</internalNodes>
      <leafValues>
        4.6129770576953888e-02 -3.4081953763961792e-01</leafValues></_>
    <_>
      <internalNodes>
        0 -1 120874 1.0304465889930725e-02</internalNodes>
      <leafValues>
        3.0927909538149834e-02 -4.5287480950355530e-01</leafValues></_>
    <_>
      <internalNodes>
        0 -1 59607 -1.4558425173163414e-02</internalNodes>
      <leafValues>
        2.6450166106224060e-01 -5.1567245274782181e-02</leafValues></_>
    <_>
      <internalNodes>
        0 -1 12395 4.3071964755654335e-03</internalNodes>
      <leafValues>
        -9.7927697002887726e-02 1.5969873964786530e-01</leafValues></_>
    <_>
      <internalNodes>
        0 -1 162159 -6.2274252995848656e-03</internalNodes>
      <leafValues>
        -5.6695735454559326e-01 2.1877458319067955e-02</leafValues></_>
    <_>
      <internalNodes>
        0 -1 161337 -3.2742305193096399e-03</internalNodes>
      <leafValues>
        4.1930395364761353e-01 -3.0593393370509148e-02</leafValues></_>
    <_>
      <internalNodes>
        0 -1 159928 -1.0774549446068704e-04</internalNodes>
      <leafValues>
        -1.6679185628890991e-01 9.1255277395248413e-02</leafValues></_>
    <_>
      <internalNodes>
        0 -1 127994 2.5032502599060535e-03</internalNodes>
      <leafValues>
        2.0287131890654564e-02 -5.5572503805160522e-01</leafValues></_>
    <_>
      <internalNodes>
        0 -1 123011 4.7889672219753265e-02</internalNodes>
      <leafValues>
        1.8341312184929848e-02 -7.0088183879852295e-01</leafValues></_>
    <_>
      <internalNodes>
        0 -1 43934 3.6469485610723495e-02</internalNodes>
      <leafValues>
        3.0361630022525787e-02 -3.9449203014373779e-01</leafValues></_>
    <_>
      <internalNodes>
        0 -1 72311 -1.9921080768108368e-01</internalNodes>
      <leafValues>
        -2.1794617176055908e-01 6.6119812428951263e-02</leafValues></_>
    <_>
      <internalNodes>
        0 -1 109993 -1.8750678002834320e-01</internalNodes>
      <leafValues>
        8.1845504045486450e-01 -1.8598027527332306e-02</leafValues></_>
    <_>
      <internalNodes>
        0 -1 56539 -1.7283268272876740e-02</internalNodes>
      <leafValues>
        2.1762080490589142e-01 -5.9329546988010406e-02</leafValues></_>
    <_>
      <internalNodes>
        0 -1 46375 -3.1162394210696220e-02</internalNodes>
      <leafValues>
        -8.6549168825149536e-01 1.9041702151298523e-02</leafValues></_>
    <_>
      <internalNodes>
        0 -1 163 -1.0056999744847417e-03</internalNodes>
      <leafValues>
        -2.5526246428489685e-01 5.3702678531408310e-02</leafValues></_>
    <_>
      <internalNodes>
        0 -1 151436 -8.3557721227407455e-03</internalNodes>
      <leafValues>
        -9.2026454210281372e-01 1.2077468447387218e-02</leafValues></_>
    <_>
      <internalNodes>
        0 -1 150612 -8.0786366015672684e-03</internalNodes>
      <leafValues>
        4.7111573815345764e-01 -3.0214274302124977e-02</leafValues></_>
    <_>
      <internalNodes>
        0 -1 161200 -7.4592547025531530e-04</internalNodes>
      <leafValues>
        1.6144344210624695e-01 -7.4732311069965363e-02</leafValues></_>
    <_>
      <internalNodes>
        0 -1 161183 3.8061165832914412e-04</internalNodes>
      <leafValues>
        6.7106269299983978e-02 -2.0141607522964478e-01</leafValues></_>
    <_>
      <internalNodes>
        0 -1 36264 5.3068464621901512e-03</internalNodes>
      <leafValues>
        -4.0667947381734848e-02 3.5407897830009460e-01</leafValues></_>
    <_>
      <internalNodes>
        0 -1 161179 -1.5706208068877459e-03</internalNodes>
      <leafValues>
        -2.9920727014541626e-01 4.9651265144348145e-02</leafValues></_>
    <_>
      <internalNodes>
        0 -1 125936 4.0930718183517456e-02</internalNodes>
      <leafValues>
        -2.8033008798956871e-02 5.3688484430313110e-01</leafValues></_>
    <_>
      <internalNodes>
        0 -1 138941 4.6736877411603928e-03</internalNodes>
      <leafValues>
        -8.4412880241870880e-02 1.5288156270980835e-01</leafValues></_>
    <_>
      <internalNodes>
        0 -1 139376 1.4035264961421490e-02</internalNodes>
      <leafValues>
        7.1783721446990967e-02 -2.1015332639217377e-01</leafValues></_>
    <_>
      <internalNodes>
        0 -1 119775 -5.7445012032985687e-02</internalNodes>
      <leafValues>
        2.6299899816513062e-01 -5.0339844077825546e-02</leafValues></_>
    <_>
      <internalNodes>
        0 -1 104790 1.9732152577489614e-03</internalNodes>
      <leafValues>
        -8.8039495050907135e-02 1.4438050985336304e-01</leafValues></_>
    <_>
      <internalNodes>
        0 -1 160723 -2.2874817252159119e-02</internalNodes>
      <leafValues>
        7.8733015060424805e-01 -1.6984039917588234e-02</leafValues></_>
    <_>
      <internalNodes>
        0 -1 69315 5.4342577641364187e-05</internalNodes>
      <leafValues>
        -1.1721558868885040e-01 1.1450292170047760e-01</leafValues></_>
    <_>
      <internalNodes>
        0 -1 63710 7.4153705500066280e-03</internalNodes>
      <leafValues>
        -4.6992406249046326e-02 2.8119200468063354e-01</leafValues></_>
    <_>
      <internalNodes>
        0 -1 121427 -3.2937570358626544e-04</internalNodes>
      <leafValues>
        -1.8243142962455750e-01 7.3418103158473969e-02</leafValues></_>
    <_>
      <internalNodes>
        0 -1 115514 4.5460965338861570e-05</internalNodes>
      <leafValues>
        -1.0818827897310257e-01 1.3390709459781647e-01</leafValues></_>
    <_>
      <internalNodes>
        0 -1 114734 2.6357072056271136e-04</internalNodes>
      <leafValues>
        9.1604426503181458e-02 -1.5664324164390564e-01</leafValues></_>
    <_>
      <internalNodes>
        0 -1 331 1.2847632169723511e-02</internalNodes>
      <leafValues>
        -5.4081331938505173e-02 2.9052188992500305e-01</leafValues></_>
    <_>
      <internalNodes>
        0 -1 160990 -7.8060949454084039e-04</internalNodes>
      <leafValues>
        -2.2119191288948059e-01 7.1369752287864685e-02</leafValues></_>
    <_>
      <internalNodes>
        0 -1 107513 -9.6683681476861238e-04</internalNodes>
      <leafValues>
        1.6893027722835541e-01 -8.2211829721927643e-02</leafValues></_>
    <_>
      <internalNodes>
        0 -1 2730 -1.8929919600486755e-01</internalNodes>
      <leafValues>
        -9.5128083229064941e-01 1.5719719231128693e-02</leafValues></_>
    <_>
      <internalNodes>
        0 -1 13488 7.9138917499221861e-05</internalNodes>
      <leafValues>
        1.0150708258152008e-01 -1.3323646783828735e-01</leafValues></_>
    <_>
      <internalNodes>
        0 -1 113761 -2.8902085032314062e-03</internalNodes>
      <leafValues>
        2.5590181350708008e-01 -4.9723796546459198e-02</leafValues></_>
    <_>
      <internalNodes>
        0 -1 49478 -2.0959214307367802e-03</internalNodes>
      <leafValues>
        -5.8132076263427734e-01 2.4240385740995407e-02</leafValues></_>
    <_>
      <internalNodes>
        0 -1 113571 -8.0130808055400848e-03</internalNodes>
      <leafValues>
        5.0543498992919922e-01 -2.7316773310303688e-02</leafValues></_>
    <_>
      <internalNodes>
        0 -1 54211 -2.3509237170219421e-01</internalNodes>
      <leafValues>
        9.3613505363464355e-01 -1.4206013642251492e-02</leafValues></_>
    <_>
      <internalNodes>
        0 -1 110598 -6.0021633544238284e-05</internalNodes>
      <leafValues>
        -1.0968074202537537e-01 1.2026122957468033e-01</leafValues></_>
    <_>
      <internalNodes>
        0 -1 47902 -1.6179308295249939e-02</internalNodes>
      <leafValues>
        4.2021703720092773e-01 -2.6112198829650879e-02</leafValues></_>
    <_>
      <internalNodes>
        0 -1 119906 8.3690239116549492e-03</internalNodes>
      <leafValues>
        3.8489434868097305e-02 -3.5966527462005615e-01</leafValues></_>
    <_>
      <internalNodes>
        0 -1 125412 -5.4540508426725864e-04</internalNodes>
      <leafValues>
        1.7902334034442902e-01 -7.4379086494445801e-02</leafValues></_>
    <_>
      <internalNodes>
        0 -1 139238 -9.4611648819409311e-05</internalNodes>
      <leafValues>
        -1.6270703077316284e-01 8.9204885065555573e-02</leafValues></_>
    <_>
      <internalNodes>
        0 -1 420 5.4141231812536716e-03</internalNodes>
      <leafValues>
        -1.1692599207162857e-01 1.2601749598979950e-01</leafValues></_>
    <_>
      <internalNodes>
        0 -1 106900 1.5695230104029179e-03</internalNodes>
      <leafValues>
        -9.2388741672039032e-02 1.4228777587413788e-01</leafValues></_>
    <_>
      <internalNodes>
        0 -1 162048 -1.6914465231820941e-04</internalNodes>
      <leafValues>
        -1.4581689238548279e-01 1.0018206387758255e-01</leafValues></_>
    <_>
      <internalNodes>
        0 -1 70435 6.8189860321581364e-03</internalNodes>
      <leafValues>
        -3.9505790919065475e-02 3.4337082505226135e-01</leafValues></_>
    <_>
      <internalNodes>
        0 -1 59739 -2.2631273604929447e-03</internalNodes>
      <leafValues>
        -3.7754848599433899e-01 4.1849449276924133e-02</leafValues></_>
    <_>
      <internalNodes>
        0 -1 162310 4.7320514568127692e-05</internalNodes>
      <leafValues>
        1.0641615092754364e-01 -1.2959840893745422e-01</leafValues></_>
    <_>
      <internalNodes>
        0 -1 3204 -6.0295785078778863e-04</internalNodes>
      <leafValues>
        -2.3167122900485992e-01 5.6265737861394882e-02</leafValues></_>
    <_>
      <internalNodes>
        0 -1 154077 2.4690963327884674e-03</internalNodes>
      <leafValues>
        -9.0999089181423187e-02 1.5555274486541748e-01</leafValues></_>
    <_>
      <internalNodes>
        0 -1 156892 -3.4688465530052781e-04</internalNodes>
      <leafValues>
        1.4860193431377411e-01 -1.1719522625207901e-01</leafValues></_>
    <_>
      <internalNodes>
        0 -1 155681 1.9911782146664336e-05</internalNodes>
      <leafValues>
        -1.3371214270591736e-01 1.2224843353033066e-01</leafValues></_>
    <_>
      <internalNodes>
        0 -1 155494 7.8945439308881760e-03</internalNodes>
      <leafValues>
        5.5557232350111008e-02 -2.8160104155540466e-01</leafValues></_>
    <_>
      <internalNodes>
        0 -1 116989 1.9114583730697632e-01</internalNodes>
      <leafValues>
        -3.3308189362287521e-02 4.3809404969215393e-01</leafValues></_>
    <_>
      <internalNodes>
        0 -1 36322 -2.0851951092481613e-02</internalNodes>
      <leafValues>
        3.2234063744544983e-01 -4.6078339219093323e-02</leafValues></_></weakClassifiers></stage14>
</opencv_storage>
